Workbook

Sheet Bills_Raw
A1: Bills_Raw (SYNTHETIC DEMO DATA) — one row per bill, all extracted fields (source of truth from the 8 PDFs)
A3: File | B3: Supply | C3: Provider | D3: Product | E3: Type | F3: Period start | G3: Period end | H3: Days | I3: Issue date | J3: kWh total | K3: kWh day | L3: kWh night | M3: Energy rate (day) | N3: Energy rate (night) | O3: Adj. clause rate | P3: Loyalty disc % | Q3: EN.A disc € | R3: Paygio €/mo | S3: A: Supply chgs € | T3: B: Regulated € | U3: Γ: Supplementary € | V3: EFK € | W3: Special 5‰ € | X3: Late interest € | Y3: E: Municipal € | Z3: ΣΤ: ERT € | AA3: VAT € | AB3: VAT base € | AC3: Enanti credit € | AD3: Prev. unpaid € | AE3: Current-period total € | AF3: Final payable €
A4: demo_d1_apr | B4: D1 | C4: Provider-A | D4: Night Floating (demo) | E4: clearing | F4: 2026-04-01 | G4: 2026-04-30 | H4: 30 | I4: 2026-05-18 | J4: 950 | K4: 700 | L4: 250 | M4: 0.155 | N4: 0.123 | P4: 0 | Q4: 0 | R4: 5 | S4: 144.25 | T4: 54.81 | U4: 2.79 | V4: 2.09 | W4: 0.7 | X4: 0 | Y4: 46 | Z4: 2.96 | AA4: 12.07 | AB4: 201.15 | AC4: 0 | AD4: 0 | AE4: 262.88 | AF4: 262.88
A5: demo_d1_may | B5: D1 | C5: Provider-A | D5: Night Floating (demo) | E5: clearing | F5: 2026-05-01 | G5: 2026-05-31 | H5: 31 | I5: 2026-06-18 | J5: 1000 | K5: 740 | L5: 260 | M5: 0.155 | N5: 0.123 | P5: 0 | Q5: 0 | R5: 5 | S5: 151.68 | T5: 57.35 | U5: 2.93 | V5: 2.2 | W5: 0.73 | X5: 0 | Y5: 47.5 | Z5: 3.06 | AA5: 12.67 | AB5: 211.23 | AC5: 0 | AD5: 0 | AE5: 275.19 | AF5: 275.19
A6: demo_d2_apr | B6: D2 | C6: Provider-B | D6: Home Floating (demo) | E6: clearing | F6: 2026-04-01 | G6: 2026-04-30 | H6: 30 | I6: 2026-05-20 | J6: 285 | K6: 285 | L6: 0 | M6: 0.157 | P6: 0 | Q6: 0 | R6: 5.5 | S6: 50.25 | T6: 15.17 | U6: 0.85 | V6: 0.63 | W6: 0.22 | X6: 0 | Y6: 5 | Z6: 2.96 | AA6: 3.96 | AB6: 66.05 | AC6: 0 | AD6: 0 | AE6: 78.19 | AF6: 78.19
A7: demo_d2_may | B7: D2 | C7: Provider-B | D7: Home Floating (demo) | E7: clearing | F7: 2026-05-01 | G7: 2026-05-31 | H7: 31 | I7: 2026-06-20 | J7: 300 | K7: 300 | L7: 0 | M7: 0.157 | P7: 0 | Q7: 0 | R7: 5.5 | S7: 52.6 | T7: 15.89 | U7: 0.9 | V7: 0.66 | W7: 0.24 | X7: 0 | Y7: 5.2 | Z7: 3.06 | AA7: 4.15 | AB7: 69.15 | AC7: 0 | AD7: 0 | AE7: 81.8 | AF7: 81.8
A8: demo_d3_apr | B8: D3 | C8: Provider-B | D8: Business Floating (demo) | E8: clearing | F8: 2026-04-01 | G8: 2026-04-30 | H8: 30 | I8: 2026-05-22 | J8: 680 | K8: 680 | L8: 0 | M8: 0.168 | P8: 0 | Q8: 0 | R8: 5.5 | S8: 119.74 | T8: 49.74 | U8: 3.97 | V8: 3.4 | W8: 0.57 | X8: 0 | Y8: 2 | Z8: 0 | AA8: 10.37 | AB8: 172.88 | AC8: 0 | AD8: 0 | AE8: 185.82 | AF8: 185.82
A9: demo_d3_may | B9: D3 | C9: Provider-B | D9: Business Floating (demo) | E9: clearing | F9: 2026-05-01 | G9: 2026-05-31 | H9: 31 | I9: 2026-06-22 | J9: 720 | K9: 720 | L9: 0 | M9: 0.168 | P9: 0 | Q9: 0 | R9: 5.5 | S9: 126.46 | T9: 52.08 | U9: 4.2 | V9: 3.6 | W9: 0.6 | X9: 0 | Y9: 2.1 | Z9: 0 | AA9: 10.93 | AB9: 182.14 | AC9: 0 | AD9: 0 | AE9: 195.77 | AF9: 195.77
A10: TOTAL | J10: =SUM(J4:J9) | S10: =SUM(S4:S9) | T10: =SUM(T4:T9) | U10: =SUM(U4:U9) | Y10: =SUM(Y4:Y9) | Z10: =SUM(Z4:Z9) | AA10: =SUM(AA4:AA9) | AE10: =SUM(AE4:AE9) | AF10: =SUM(AF4:AF9)
A12: Notes: (1) 5d2516a2 is a 66-day clearing bill whose payable (280.19) is NET of a 224.95€ 'enanti' (on-account) charge billed earlier. Its true economic period cost is reconstructed gross = 518.64€ (see Backtest). (2) VAT (6%) base = A + B + EFK. Municipal, ERT, special 5‰ and late interest are outside the VAT base. (3) EFK = 0.0022 €/kWh residential, 0.005 €/kWh business. (4) S4 (DEH) April municipal/ERT split estimated; aggregate exact.

Sheet Supplies
A1: Supplies — one row per electricity supply/contract
A3: Supply ID | B3: Provider (now) | C3: Supply number | D3: Property / label | E3: Customer type | F3: Current product | G3: Tariff type | H3: Power (kVA) | I3: Phases | J3: Register | K3: Priority | L3: Bills count | M3: Total kWh (sampled) | N3: Total days (sampled) | O3: Avg kWh/day | P3: Annualised kWh est. | Q3: Notes
A4: D1 | B4: Provider-A | C4: 0-00000000-0 | D4: DEMO — Main residence (night tariff) | E4: residential | F4: Night Floating (demo) | G4: floating night | H4: 35 | I4: 3 | J4: dual (day/night) | K4: HIGH | L4: 2 | M4: 1950 | N4: 61 | O4: 31.97 | P4: 11668 | Q4: Synthetic. High consumption ~950 kWh/mo, ~30% on night register.
A5: D2 | B5: Provider-B | C5: 0-00000000-1 | D5: DEMO — Apartment | E5: residential | F5: Home Floating (demo) | G5: floating | H5: 8 | I5: 1 | J5: single | K5: medium | L5: 2 | M5: 585 | N5: 61 | O5: 9.59 | P5: 3500 | Q5: Synthetic. ~280 kWh/mo single-register.
A6: D3 | B6: Provider-B | C6: 0-00000000-2 | D6: DEMO — Building common areas | E6: business | F6: Business Floating (demo) | G6: floating business | H6: 25 | I6: 3 | J6: single | K6: medium | L6: 2 | M6: 1400 | N6: 61 | O6: 22.95 | P6: 8377 | Q6: Synthetic. Common areas (koinochrista), 25 kVA, ~700 kWh/mo.

Sheet Bill_Line_Items
A1: Bill_Line_Items — detailed line items per bill
A3: File | B3: Supply | C3: Category | D3: Line item | E3: Basis / calc | F3: Amount € | G3: Provider-dependent?
A4: demo_d1_apr | B4: D1 | C4: A Supply | D4: Paygio (fixed) | E4: 5.00€ for 30d | F4: 5 | G4: YES
A5: demo_d1_apr | B5: D1 | C5: A Supply | D5: Energy DAY (kanoniki) | E5: 700 kWh x 0.155 €/kWh | F5: 108.5 | G5: YES
A6: demo_d1_apr | B6: D1 | C6: A Supply | D6: Energy NIGHT (meiomeni) | E6: 250 kWh x 0.123 €/kWh | F6: 30.75 | G6: YES
A7: demo_d1_apr | B7: D1 | C7: B Regulated | D7: ADMIE+DEDDIE+ETMEAR+YKO | E7: transmission+distribution+RES levy+PSO (regulated) | F7: 54.81 | G7: no
A8: demo_d1_apr | B8: D1 | C8: Taxes | D8: EFK (excise) | E8: 2.09 (in VAT base) | F8: 2.09 | G8: no
A9: demo_d1_apr | B9: D1 | C9: Taxes | D9: Special levy 5‰ | E9: 0.5% of energy value | F9: 0.7 | G9: no
A10: demo_d1_apr | B10: D1 | C10: Municipal | D10: DT+DF+TAP (Dimos) | E10: per m2 / municipality | F10: 46 | G10: no
A11: demo_d1_apr | B11: D1 | C11: ERT | D11: ERT levy | E11: 36€/yr prorated | F11: 2.96 | G11: no
A12: demo_d1_apr | B12: D1 | C12: VAT | D12: VAT 6% | E12: 6% x 201.15 | F12: 12.07 | G12: no (follows A)
A14: demo_d1_may | B14: D1 | C14: A Supply | D14: Paygio (fixed) | E14: 5.00€ for 31d | F14: 5 | G14: YES
A15: demo_d1_may | B15: D1 | C15: A Supply | D15: Energy DAY (kanoniki) | E15: 740 kWh x 0.155 €/kWh | F15: 114.7 | G15: YES
A16: demo_d1_may | B16: D1 | C16: A Supply | D16: Energy NIGHT (meiomeni) | E16: 260 kWh x 0.123 €/kWh | F16: 31.98 | G16: YES
... A58: demo_d3_may | B58: D3 | C58: VAT | D58: VAT 6% | E58: 6% x 182.14 | F58: 10.93 | G58: no (follows A)

Sheet Fee_Model
A1: Fee_Model — how each charge is calculated and whether switching provider changes it
A3: Charge | B3: What it is | C3: Who charges | D3: Basis (depends on) | E3: Changes with provider? | F3: Avoidable/reducible? | G3: How modelled in Excel
A4: Paygio (fixed supply fee) | B4: Monthly standing charge of the supplier | C4: Supplier (DEH/HERON/...) | D4: Days (prorated) | E4: YES | F4: Yes – pick low/zero-paygio offer | G4: paygio_monthly × days/30
A5: Energy charge | B5: Competitive price for kWh consumed | C5: Supplier | D5: kWh (× day/night if dual) | E5: YES | F5: Yes – core of the comparison | G5: kWh × rate (×(1-disc))
A6: Market adjustment clause (Diakymansi Kostous Agoras / ritra) | B6: Pass-through of wholesale market cost on floating products | C6: Supplier | D6: kWh | E6: YES | F6: Yes – fixed-price product removes it | G6: included in effective rate; 0 for fixed products
A7: Loyalty / quantity / consistency discount | B7: Discount for staying / paying on time / direct debit | C7: Supplier | D7: % of energy or fixed | E7: YES | F7: Yes – maximise by qualifying | G7: applied as % off energy or fixed €
A8: ADMIE (Transmission / Systima Metaforas) | B8: Use of the high-voltage transmission grid | C8: ADMIE (regulated) | D8: kWh (+kVA capacity) | E8: NO – same for all suppliers | F8: No | G8: kept as actual; pass-through unchanged
A9: DEDDIE (Distribution / Diktyo Dianomis) | B9: Use of the low/medium-voltage distribution grid | C9: DEDDIE (regulated) | D9: kVA capacity × days + kWh | E9: NO – same for all | F9: No | G9: kept as actual; pass-through unchanged
A10: ETMEAR | B10: Levy financing renewables (RES special account) | C10: State/regulated | D10: kWh | E10: NO – same for all | F10: No | G10: kept as actual (0.017 €/kWh observed)
A11: YKO (Public Service Obligations) | B11: Funds subsidised tariffs/island supply | C11: State/regulated | D11: kWh (tiered; night band) | E11: NO – same for all | F11: No | G11: kept as actual
A12: EFK (Excise / Eidikos Foros Katanalosis) | B12: State excise on electricity | C12: State | D12: kWh | E12: NO | F12: No | G12: 0.0022 €/kWh resid., 0.005 business; in VAT base
A13: Special levy 5‰ (N.2093/92) | B13: Stamp-type special duty | C13: State | D13: 0.5% of energy value | E13: NO | F13: No | G13: kept as actual; outside VAT base
A14: Municipal fees DT/DF (Dimotika Teli/Foros) | B14: Cleaning & lighting municipal charge | C14: Municipality (collected via bill) | D14: m2 of property × municipal rate × days | E14: NO – property-based | F14: No (unless m2/municipality data wrong) | G14: kept as actual; outside VAT base
... A18: Government subsidy (Kratiki Epidotisi T.E.M.) | B18: Temporary state subsidy on energy when active | C18: State | D18: kWh when triggered | E18: Applies to all | F18: n/a | G18: 0 in these bills (none active)

Sheet Market_Offers
A1: Market_Offers — researched current Greek offers (see source URLs & dates)
A3: Offer ID | B3: Provider | C3: Product | D3: Color/Category | E3: Type | F3: Segment | G3: Energy €/kWh | H3: Night €/kWh | I3: Adj. clause? | J3: Paygio €/mo | K3: Net disc % (qualified) | L3: Disc conditions | M3: Contract | N3: Exit penalty | O3: High-consumption OK? | P3: Source URL | Q3: Researched
A4: OFF_FIXNIGHT | B4: Provider-A | C4: Fixed Night 24M (demo) | D4: Blue | E4: fixed-night | F4: resi-night | G4: 0.145 | H4: 0.105 | I4: no | J4: 9 | K4: 0 | L4: fixed; demo | M4: 24 months fixed | N4: demo | O4: yes | P4: DEMO — verify on energycost.gr | Q4: 2026-06-24
A5: OFF_FLOATNIGHT | B5: Provider-C | C5: Floating Night (demo) | D5: Yellow | E5: floating-night | F5: resi-night | G5: 0.1133 | H5: 0.1033 | I5: yes | J5: 5 | K5: 0 | L5: reprices monthly; demo | M5: none | N5: none | O5: yes | P5: DEMO — verify on energycost.gr | Q5: 2026-06-24
A6: OFF_ZEROPAGIO | B6: Provider-D | C6: Zero-Paygio Home (demo) | D6: Yellow | E6: floating | F6: resi | G6: 0.134 | I6: yes | J6: 0 | K6: 0 | L6: zero standing charge; demo | M6: none | N6: none | O6: yes | P6: DEMO — verify on energycost.gr | Q6: 2026-06-24
A7: OFF_FIXHOME | B7: Provider-E | C7: Fixed Home 12M (demo) | D7: Blue | E7: fixed | F7: resi | G7: 0.139 | I7: no | J7: 9.9 | K7: 0 | L7: fixed; demo | M7: 12 months fixed | N7: demo | O7: yes | P7: DEMO — verify on energycost.gr | Q7: 2026-06-24
A8: OFF_COSTPLUS | B8: Provider-C | C8: Cost+ Home (demo) | D8: Yellow | E8: floating | F8: resi | G8: 0.122 | I8: yes | J8: 7.1 | K8: 0 | L8: cost-plus floating; demo | M8: none | N8: none | O8: yes | P8: DEMO — verify on energycost.gr | Q8: 2026-06-24
A9: OFF_BUSGREEN | B9: Provider-D | C9: Business Green (demo) | D9: Green | E9: floating-business | F9: business | G9: 0.118 | I9: yes | J9: 0 | K9: 0 | L9: low-margin business green; CONFIRM it accepts a koinochrista meter (demo) | M9: none | N9: none | O9: yes | P9: DEMO — verify on energycost.gr | Q9: 2026-06-24
A10: OFF_BUSSAVER | B10: Provider-B | C10: Business Saver (demo) | D10: Yellow | E10: floating-business | F10: business | G10: 0.133 | I10: yes | J10: 5.5 | K10: 0 | L10: common-areas <=25kVA; demo | M10: none | N10: none | O10: yes | P10: DEMO — verify on energycost.gr | Q10: 2026-06-24
A11: OFF_BUSFIX | B11: Provider-E | C11: Business Fixed 12M (demo) | D11: Blue | E11: fixed-business | F11: business | G11: 0.17 | I11: no | J11: 13.9 | K11: 0 | L11: fixed business; demo | M11: 12 months fixed | N11: demo | O11: yes | P11: DEMO — verify on energycost.gr | Q11: 2026-06-24

Sheet Scenario_Model
A1: Scenario_Model — estimated ANNUAL competitive-supply cost (component A only) of each offer on each supply
A2: Shows only the provider-dependent part (A = paygio + energy - discounts) annualised on each supply's sampled consumption (NB: scaled from a short, not-seasonally-representative sample). Regulated/municipal/ERT/taxes are identical across providers and are excluded here (they are added back in Backtest). Night-tariff supply S4 priced on TOTAL kWh at the offer's day rate unless the offer has a night rate (conservative).
A4: Offer ID | B4: Provider | C4: Product | D4: D1 Prov ann.A € | E4: D2 Prov ann.A € | F4: D3 Prov ann.A €
A5: OFF_FIXNIGHT | B5: Provider-A | C5: Fixed Night 24M (demo) | D5: ='Market_Offers'!J4*12 + IF('Market_Offers'!H4>0,(8616.4*'Market_Offers'!G4+3051.6*'Market_Offers'!H4),11668.0*'Market_Offers'!G4)*(1-'Market_Offers'!K4) | E5: ='Market_Offers'!J4*12 + IF('Market_Offers'!H4>0,(3500.4*'Market_Offers'!G4+0.0*'Market_Offers'!H4),3500.4*'Market_Offers'!G4)*(1-'Market_Offers'!K4) | F5: ='Market_Offers'!J4*12 + IF('Market_Offers'!H4>0,(8377.0*'Market_Offers'!G4+0.0*'Market_Offers'!H4),8377.0*'Market_Offers'!G4)*(1-'Market_Offers'!K4)
A6: OFF_FLOATNIGHT | B6: Provider-C | C6: Floating Night (demo) | D6: ='Market_Offers'!J5*12 + IF('Market_Offers'!H5>0,(8616.4*'Market_Offers'!G5+3051.6*'Market_Offers'!H5),11668.0*'Market_Offers'!G5)*(1-'Market_Offers'!K5) | E6: ='Market_Offers'!J5*12 + IF('Market_Offers'!H5>0,(3500.4*'Market_Offers'!G5+0.0*'Market_Offers'!H5),3500.4*'Market_Offers'!G5)*(1-'Market_Offers'!K5) | F6: ='Market_Offers'!J5*12 + IF('Market_Offers'!H5>0,(8377.0*'Market_Offers'!G5+0.0*'Market_Offers'!H5),8377.0*'Market_Offers'!G5)*(1-'Market_Offers'!K5)
A7: OFF_ZEROPAGIO | B7: Provider-D | C7: Zero-Paygio Home (demo) | D7: ='Market_Offers'!J6*12 + IF('Market_Offers'!H6>0,(8616.4*'Market_Offers'!G6+3051.6*'Market_Offers'!H6),11668.0*'Market_Offers'!G6)*(1-'Market_Offers'!K6) | E7: ='Market_Offers'!J6*12 + IF('Market_Offers'!H6>0,(3500.4*'Market_Offers'!G6+0.0*'Market_Offers'!H6),3500.4*'Market_Offers'!G6)*(1-'Market_Offers'!K6) | F7: ='Market_Offers'!J6*12 + IF('Market_Offers'!H6>0,(8377.0*'Market_Offers'!G6+0.0*'Market_Offers'!H6),8377.0*'Market_Offers'!G6)*(1-'Market_Offers'!K6)
A8: OFF_FIXHOME | B8: Provider-E | C8: Fixed Home 12M (demo) | D8: ='Market_Offers'!J7*12 + IF('Market_Offers'!H7>0,(8616.4*'Market_Offers'!G7+3051.6*'Market_Offers'!H7),11668.0*'Market_Offers'!G7)*(1-'Market_Offers'!K7) | E8: ='Market_Offers'!J7*12 + IF('Market_Offers'!H7>0,(3500.4*'Market_Offers'!G7+0.0*'Market_Offers'!H7),3500.4*'Market_Offers'!G7)*(1-'Market_Offers'!K7) | F8: ='Market_Offers'!J7*12 + IF('Market_Offers'!H7>0,(8377.0*'Market_Offers'!G7+0.0*'Market_Offers'!H7),8377.0*'Market_Offers'!G7)*(1-'Market_Offers'!K7)
A9: OFF_COSTPLUS | B9: Provider-C | C9: Cost+ Home (demo) | D9: ='Market_Offers'!J8*12 + IF('Market_Offers'!H8>0,(8616.4*'Market_Offers'!G8+3051.6*'Market_Offers'!H8),11668.0*'Market_Offers'!G8)*(1-'Market_Offers'!K8) | E9: ='Market_Offers'!J8*12 + IF('Market_Offers'!H8>0,(3500.4*'Market_Offers'!G8+0.0*'Market_Offers'!H8),3500.4*'Market_Offers'!G8)*(1-'Market_Offers'!K8) | F9: ='Market_Offers'!J8*12 + IF('Market_Offers'!H8>0,(8377.0*'Market_Offers'!G8+0.0*'Market_Offers'!H8),8377.0*'Market_Offers'!G8)*(1-'Market_Offers'!K8)
A10: OFF_BUSGREEN | B10: Provider-D | C10: Business Green (demo) | D10: ='Market_Offers'!J9*12 + IF('Market_Offers'!H9>0,(8616.4*'Market_Offers'!G9+3051.6*'Market_Offers'!H9),11668.0*'Market_Offers'!G9)*(1-'Market_Offers'!K9) | E10: ='Market_Offers'!J9*12 + IF('Market_Offers'!H9>0,(3500.4*'Market_Offers'!G9+0.0*'Market_Offers'!H9),3500.4*'Market_Offers'!G9)*(1-'Market_Offers'!K9) | F10: ='Market_Offers'!J9*12 + IF('Market_Offers'!H9>0,(8377.0*'Market_Offers'!G9+0.0*'Market_Offers'!H9),8377.0*'Market_Offers'!G9)*(1-'Market_Offers'!K9)
A11: OFF_BUSSAVER | B11: Provider-B | C11: Business Saver (demo) | D11: ='Market_Offers'!J10*12 + IF('Market_Offers'!H10>0,(8616.4*'Market_Offers'!G10+3051.6*'Market_Offers'!H10),11668.0*'Market_Offers'!G10)*(1-'Market_Offers'!K10) | E11: ='Market_Offers'!J10*12 + IF('Market_Offers'!H10>0,(3500.4*'Market_Offers'!G10+0.0*'Market_Offers'!H10),3500.4*'Market_Offers'!G10)*(1-'Market_Offers'!K10) | F11: ='Market_Offers'!J10*12 + IF('Market_Offers'!H10>0,(8377.0*'Market_Offers'!G10+0.0*'Market_Offers'!H10),8377.0*'Market_Offers'!G10)*(1-'Market_Offers'!K10)
A12: OFF_BUSFIX | B12: Provider-E | C12: Business Fixed 12M (demo) | D12: ='Market_Offers'!J11*12 + IF('Market_Offers'!H11>0,(8616.4*'Market_Offers'!G11+3051.6*'Market_Offers'!H11),11668.0*'Market_Offers'!G11)*(1-'Market_Offers'!K11) | E12: ='Market_Offers'!J11*12 + IF('Market_Offers'!H11>0,(3500.4*'Market_Offers'!G11+0.0*'Market_Offers'!H11),3500.4*'Market_Offers'!G11)*(1-'Market_Offers'!K11) | F12: ='Market_Offers'!J11*12 + IF('Market_Offers'!H11>0,(8377.0*'Market_Offers'!G11+0.0*'Market_Offers'!H11),8377.0*'Market_Offers'!G11)*(1-'Market_Offers'!K11)

Sheet Backtest
A1: Backtest — what each ACTUAL bill would have cost under the recommended alternative
A2: Method: replace component A (supplier paygio+energy-discounts) with the recommended offer; keep B (regulated), municipal, ERT and taxes EXACTLY as billed; recompute VAT = 6% × (newA + B + EFK). 5d2516a2 uses gross reconstruction (its payable is net of a 224.95€ on-account charge). Change the offer rates in Market_Offers and this recalculates.
A4: File | B4: Supply | C4: Rec. offer | D4: Days | E4: kWh | F4: Actual A € | G4: Fixed non-A (B+tax+muni+ERT) € | H4: Actual VAT € | I4: Actual total € | J4: New A € | K4: New VAT € | L4: New total € | M4: Saving € | N4: Saving %
A5: demo_d1_apr | B5: D1 | C5: OFF_FIXNIGHT | D5: 30 | E5: 950 | F5: 144.25 | G5: 106.56 | H5: 12.07 | I5: 262.88 | J5: ='Market_Offers'!J4*30/30 + IF('Market_Offers'!H4>0,(700*'Market_Offers'!G4+250*'Market_Offers'!H4),950*'Market_Offers'!G4)*(1-'Market_Offers'!K4) | K5: =0.06*(J5+56.90) | L5: =106.56+J5+K5 | M5: =I5-L5 | N5: =IF(I5=0,0,M5/I5)
A6: demo_d1_may | B6: D1 | C6: OFF_FIXNIGHT | D6: 31 | E6: 1000 | F6: 151.68 | G6: 110.84 | H6: 12.67 | I6: 275.19 | J6: ='Market_Offers'!J4*31/30 + IF('Market_Offers'!H4>0,(740*'Market_Offers'!G4+260*'Market_Offers'!H4),1000*'Market_Offers'!G4)*(1-'Market_Offers'!K4) | K6: =0.06*(J6+59.55) | L6: =110.84+J6+K6 | M6: =I6-L6 | N6: =IF(I6=0,0,M6/I6)
A7: demo_d2_apr | B7: D2 | C7: OFF_ZEROPAGIO | D7: 30 | E7: 285 | F7: 50.25 | G7: 23.98 | H7: 3.96 | I7: 78.19 | J7: ='Market_Offers'!J6*30/30 + IF('Market_Offers'!H6>0,(285*'Market_Offers'!G6+0*'Market_Offers'!H6),285*'Market_Offers'!G6)*(1-'Market_Offers'!K6) | K7: =0.06*(J7+15.80) | L7: =23.98+J7+K7 | M7: =I7-L7 | N7: =IF(I7=0,0,M7/I7)
A8: demo_d2_may | B8: D2 | C8: OFF_ZEROPAGIO | D8: 31 | E8: 300 | F8: 52.6 | G8: 25.05 | H8: 4.15 | I8: 81.8 | J8: ='Market_Offers'!J6*31/30 + IF('Market_Offers'!H6>0,(300*'Market_Offers'!G6+0*'Market_Offers'!H6),300*'Market_Offers'!G6)*(1-'Market_Offers'!K6) | K8: =0.06*(J8+16.55) | L8: =25.05+J8+K8 | M8: =I8-L8 | N8: =IF(I8=0,0,M8/I8)
A9: demo_d3_apr | B9: D3 | C9: OFF_BUSSAVER | D9: 30 | E9: 680 | F9: 119.74 | G9: 55.71 | H9: 10.37 | I9: 185.82 | J9: ='Market_Offers'!J10*30/30 + IF('Market_Offers'!H10>0,(680*'Market_Offers'!G10+0*'Market_Offers'!H10),680*'Market_Offers'!G10)*(1-'Market_Offers'!K10) | K9: =0.06*(J9+53.14) | L9: =55.71+J9+K9 | M9: =I9-L9 | N9: =IF(I9=0,0,M9/I9)
A10: demo_d3_may | B10: D3 | C10: OFF_BUSSAVER | D10: 31 | E10: 720 | F10: 126.46 | G10: 58.38 | H10: 10.93 | I10: 195.77 | J10: ='Market_Offers'!J10*31/30 + IF('Market_Offers'!H10>0,(720*'Market_Offers'!G10+0*'Market_Offers'!H10),720*'Market_Offers'!G10)*(1-'Market_Offers'!K10) | K10: =0.06*(J10+55.68) | L10: =58.38+J10+K10 | M10: =I10-L10 | N10: =IF(I10=0,0,M10/I10)
A11: TOTAL | E11: =SUM(E5:E10) | F11: =SUM(F5:F10) | G11: =SUM(G5:G10) | H11: =SUM(H5:H10) | I11: =SUM(I5:I10) | J11: =SUM(J5:J10) | K11: =SUM(K5:K10) | L11: =SUM(L5:L10) | M11: =SUM(M5:M10) | N11: =M11/I11
A13: Per-supply summary (current-period samples)
A14: Supply | B14: Provider now | C14: Rec. offer | D14: Actual total € | E14: New total € | F14: Saving € | G14: Saving %
A15: D1 | B15: Provider-A | C15: OFF_FIXNIGHT | D15: =I5+I6 | E15: =L5+L6 | F15: =D15-E15 | G15: =F15/D15
A16: D2 | B16: Provider-B | C16: OFF_ZEROPAGIO | D16: =I7+I8 | E16: =L7+L8 | F16: =D16-E16 | G16: =F16/D16
A17: D3 | B17: Provider-B | C17: OFF_BUSSAVER | D17: =I9+I10 | E17: =L9+L10 | F17: =D17-E17 | G17: =F17/D17

Sheet Tier_Ranking
A1: Tier_Ranking — decide commit-to-a-price vs follow-the-market FIRST, then compare within the tier
A2: Floating, 1-year fixed and multi-year fixed are different RISK products, not one price line. Per supply, offers are grouped by commitment tier and ranked cheapest-first WITHIN each tier (computed on the sampled bills; re-run the builder after editing Market_Offers). Weigh the fixed term: a long lock in a volatile market is opportunity risk + an exit fee, not free certainty. Cheapest in each tier is highlighted.
A4: D1 — DEMO — Main residence (night tariff) · current actual (sample): €538.07
A5: Offer | B5: Provider | C5: Color | D5: Term | E5: Eff. €/kWh | F5: New total (sample) € | G5: Saving € | H5: Saving %
A6: Floating — follow the market
A7: Floating Night (demo) | B7: Provider-C | C7: Yellow | D7: none | E7: 0.1133 | F7: 463.95 | G7: 74.12 | H7: 0.13775389
A8: Cost+ Home (demo) | B8: Provider-C | C8: Yellow | D8: none | E8: 0.122 | F8: 491.86 | G8: 46.21 | H8: 0.085873833
A9: Zero-Paygio Home (demo) | B9: Provider-D | C9: Yellow | D9: none | E9: 0.134 | F9: 501.37 | G9: 36.7 | H9: 0.068216031
A10: Fixed ≤ 12 months
A11: Fixed Home 12M (demo) | B11: Provider-E | C11: Blue | D11: 12 months fixed | E11: 0.139 | F11: 533.04 | G11: 5.03 | H11: 0.0093523148
A12: Fixed 13–24 months
A13: Fixed Night 24M (demo) | B13: Provider-A | C13: Blue | D13: 24 months fixed | E13: 0.145 | F13: 521.88 | G13: 16.19 | H13: 0.030096456
A15: D2 — DEMO — Apartment · current actual (sample): €159.99
A16: Offer | B16: Provider | C16: Color | D16: Term | E16: Eff. €/kWh | F16: New total (sample) € | G16: Saving € | H16: Saving %
A17: Floating — follow the market
A18: Zero-Paygio Home (demo) | B18: Provider-D | C18: Yellow | D18: none | E18: 0.134 | F18: 134.06 | G18: 25.93 | H18: 0.16204513
A19: Cost+ Home (demo) | B19: Provider-C | C19: Yellow | D19: none | E19: 0.122 | F19: 141.93 | G19: 18.06 | H19: 0.11290664
A20: Fixed ≤ 12 months
A21: Fixed Home 12M (demo) | B21: Provider-E | C21: Blue | D21: 12 months fixed | E21: 0.139 | F21: 158.5 | G21: 1.49 | H21: 0.009296206
A23: D3 — DEMO — Building common areas · current actual (sample): €381.59
A24: Offer | B24: Provider | C24: Color | D24: Term | E24: Eff. €/kWh | F24: New total (sample) € | G24: Saving € | H24: Saving %
A25: Floating — follow the market
A26: Business Green (demo) | B26: Provider-D | C26: Green | D26: none | E26: 0.118 | F26: 295.73 | G26: 85.86 | H26: 0.22500275
A27: Business Saver (demo) | B27: Provider-B | C27: Yellow | D27: none | E27: 0.133 | F27: 329.85 | G27: 51.74 | H27: 0.13560226
A28: Fixed ≤ 12 months
A29: Business Fixed 12M (demo) | B29: Provider-E | C29: Blue | D29: 12 months fixed | E29: 0.17 | F29: 402.86 | G29: -21.27 | H29: -0.055736087

Sheet Recommendation
A1: Recommendation — best move per supply
A3: Supply | B3: Property | C3: Priority | D3: Provider now → product | E3: Recommended → product | F3: Why | G3: Est. monthly saving € | H3: Action
A4: D1 | B4: DEMO — Main residence (night tariff) | C4: HIGH | D4: Provider-A → Night Floating (demo) | E4: Provider-A → Fixed Night 24M (demo) | F4: Main residence on a floating night tariff (effective ~0.155 day / ~0.123 night). A FIXED dual-zone product (day 0.145 / night 0.105) is lower on both registers and removes the monthly-reset risk — the conservative pick for the priority contract. A floating dual-zone (Provider-C, day 0.1133 / night 0.1033) would save more but reintroduces price risk. | H4: Switch to a fixed dual-zone tariff; keep the night meter. (Demo.)
A5: D2 | B5: DEMO — Apartment | C5: medium | D5: Provider-B → Home Floating (demo) | E5: Provider-D → Zero-Paygio Home (demo) | F5: Apartment at ~280 kWh/month — low enough that the standing charge dominates, so a ZERO-paygio plan wins even at a slightly higher rate. Beats a low-rate/high-paygio fixed plan here. | H5: Switch to a zero-paygio floating plan. (Demo.)
A6: D3 | B6: DEMO — Building common areas | C6: medium | D6: Provider-B → Business Floating (demo) | E6: Provider-B → Business Saver (demo) | F6: Common areas (business, 25 kVA) on an expensive floating product (~0.168). A cheaper business floating (~0.133) saves materially. A non-incumbent low-margin business green (~0.118, zero paygio) would save even more — but only IF it accepts a koinochrista meter; confirm before choosing it. A fixed business product here (~0.17) is NOT cheaper than the floating you already have. | H6: Switch to a cheaper business floating; chase the zero-paygio business green only if it accepts your common-area meter. (Demo.)
A9: Overall expected savings: see Backtest TOTAL row. Headline figures are summarised in the report.
